geoengine/__init__.py
geoengine/auth.py
geoengine/datasets.py
geoengine/error.py
geoengine/types.py
geoengine/workflow.py
tests/__init__.py
tests/test_auth.py
tests/test_plot.py
tests/test_provenance.py
tests/test_upload.py
tests/test_wcs.py
tests/test_wfs.py
tests/test_wms.py
tests/test_workflow_storage.py
geoengine-0.7.0.dist-info/LICENSE
geoengine-0.7.0.dist-info/METADATA
geoengine-0.7.0.dist-info/WHEEL
geoengine-0.7.0.dist-info/top_level.txt
geoengine-0.7.0.dist-info/RECORD
