Metadata-Version: 2.1
Name: geoengine
Version: 0.7.0
Summary: A package for easy access to Geo Engine instances
Home-page: https://github.com/geo-engine/geoengine-python
Author: Geo Engine GmbH
Author-email: info@geoengine.de
License: UNKNOWN
Project-URL: Bug Tracker, https://github.com/geo-engine/geoengine-python
Platform: UNKNOWN
Classifier: Programming Language :: Python :: 3
Classifier: Topic :: Database :: Front-Ends
Requires-Python: >=3.7
License-File: LICENSE
Requires-Dist: geopandas (<0.11,>=0.9)
Requires-Dist: numpy (<2,>=1.21)
Requires-Dist: owslib (<0.26,>=0.25)
Requires-Dist: pillow (<10,>=9.0)
Requires-Dist: python-dotenv (<0.20,>=0.19)
Requires-Dist: rasterio (<2,>=1.2)
Requires-Dist: requests (<3,>=2.26)
Requires-Dist: vega (<4,>=3.5)
Requires-Dist: xarray (<0.20,>=0.19)
Provides-Extra: dev
Requires-Dist: build (<0.8,>=0.7) ; extra == 'dev'
Requires-Dist: pdoc3 (<0.11,>=0.10) ; extra == 'dev'
Requires-Dist: pycodestyle (<3,>=2.8) ; extra == 'dev'
Requires-Dist: pylint (<3,>=2.11) ; extra == 'dev'
Requires-Dist: setuptools (<61,>=42) ; extra == 'dev'
Requires-Dist: twine (<4,>=3.4) ; extra == 'dev'
Requires-Dist: wheel (<0.38,>=0.37) ; extra == 'dev'
Provides-Extra: examples
Requires-Dist: cartopy (==0.19.0.post1) ; extra == 'examples'
Requires-Dist: matplotlib (<4,>=3.4) ; extra == 'examples'
Requires-Dist: scipy (<2,>=1.7) ; extra == 'examples'
Provides-Extra: test
Requires-Dist: matplotlib (<4,>=3.4) ; extra == 'test'
Requires-Dist: pytest (<7,>=6.2) ; extra == 'test'
Requires-Dist: requests-mock (<2,>=1.9) ; extra == 'test'
